pyrsslocal/__init__.py
pyrsslocal/custom_server/__init__.py
pyrsslocal/custom_server/aserver.py
pyrsslocal/helper/__init__.py
pyrsslocal/helper/download_helper.py
pyrsslocal/helper/python_run.py
pyrsslocal/helper/search_engine.py
pyrsslocal/helper/subscription_helper.py
pyrsslocal/javascript/__init__.py
pyrsslocal/javascript/d3.v3.js
pyrsslocal/javascript/d3.v3.min.js
pyrsslocal/javascript/desert.css
pyrsslocal/javascript/doxy.css
pyrsslocal/javascript/jquery-1.9.1.min.js
pyrsslocal/javascript/lang-apollo.js
pyrsslocal/javascript/lang-basic.js
pyrsslocal/javascript/lang-clj.js
pyrsslocal/javascript/lang-css.js
pyrsslocal/javascript/lang-dart.js
pyrsslocal/javascript/lang-erlang.js
pyrsslocal/javascript/lang-go.js
pyrsslocal/javascript/lang-hs.js
pyrsslocal/javascript/lang-lisp.js
pyrsslocal/javascript/lang-llvm.js
pyrsslocal/javascript/lang-lua.js
pyrsslocal/javascript/lang-matlab.js
pyrsslocal/javascript/lang-ml.js
pyrsslocal/javascript/lang-mumps.js
pyrsslocal/javascript/lang-n.js
pyrsslocal/javascript/lang-pascal.js
pyrsslocal/javascript/lang-proto.js
pyrsslocal/javascript/lang-r.js
pyrsslocal/javascript/lang-rd.js
pyrsslocal/javascript/lang-scala.js
pyrsslocal/javascript/lang-sql.js
pyrsslocal/javascript/lang-tcl.js
pyrsslocal/javascript/lang-tex.js
pyrsslocal/javascript/lang-vb.js
pyrsslocal/javascript/lang-vhdl.js
pyrsslocal/javascript/lang-wiki.js
pyrsslocal/javascript/lang-xq.js
pyrsslocal/javascript/lang-yaml.js
pyrsslocal/javascript/latexit.js
pyrsslocal/javascript/pMenu.css
pyrsslocal/javascript/pMenu.js
pyrsslocal/javascript/prettify.css
pyrsslocal/javascript/prettify.js
pyrsslocal/javascript/run_prettify.js
pyrsslocal/javascript/sons-of-obsidian.css
pyrsslocal/javascript/sunburst.css
pyrsslocal/rss/__init__.py
pyrsslocal/rss/all.png
pyrsslocal/rss/arrowi.png
pyrsslocal/rss/frequent.png
pyrsslocal/rss/notfrequent.png
pyrsslocal/rss/rss_blogpost.py
pyrsslocal/rss/rss_database.py
pyrsslocal-0.8.250.dist-info/DESCRIPTION.rst
pyrsslocal-0.8.250.dist-info/METADATA
pyrsslocal-0.8.250.dist-info/RECORD
pyrsslocal-0.8.250.dist-info/WHEEL
pyrsslocal-0.8.250.dist-info/metadata.json
pyrsslocal-0.8.250.dist-info/top_level.txt
