Metadata-Version: 2.0
Name: pyrsslocal
Version: 0.8.250
Summary: Local RSS reader/viewer
Home-page: http://www.xavierdupre.fr/app/pyrsslocal/helpsphinx/index.html
Author: Xavier Dupré
Author-email: xavier.dupre@gmail.com
License: MIT
Download-URL: https://github.com/sdpython/pyrsslocal/
Keywords: pyrsslocal,RSS,viewer,blog,post
Platform: UNKNOWN
Classifier: Programming Language :: Python :: 3
Classifier: Intended Audience :: Developers
Classifier: Topic :: Scientific/Engineering
Classifier: Topic :: Education
Classifier: License :: OSI Approved :: MIT License
Classifier: Development Status :: 5 - Production/Stable
Requires-Dist: pyquickhelper
Requires-Dist: pyensae
Requires-Dist: feedparser
